unfat/__init__.py
unfat/axolotl.py
unfat/client.py
unfat/datasets.py
unfat/extract.py
unfat/lora.py
unfat/py.typed
unfat/together.py
unfat-0.0.13.dist-info/METADATA
unfat-0.0.13.dist-info/WHEEL
unfat-0.0.13.dist-info/top_level.txt
unfat-0.0.13.dist-info/RECORD
