Metadata-Version: 2.2
Name: unfat
Version: 0.0.13
Summary: Extract datasets from models and train slimmer LoRAs on them
Author: @reissbaker
License: MIT
Keywords: finetune,LoRA,llm
Requires-Python: <4.0,>=3.11
Requires-Dist: tqdm<5.0.0,>=4.67.1
Requires-Dist: datasets<4.0.0,>=3.2.0
Requires-Dist: aiohttp<4.0.0,>=3.11.11
Requires-Dist: pylint<4.0.0,>=3.3.4
Requires-Dist: mypy<2.0.0,>=1.14.1
Requires-Dist: pyyaml<7.0.0,>=6.0.2
Requires-Dist: together<2.0.0,>=1.4.1
